[{
    "rownumber": "1",
    "empName": "柴新原",
    "EMAIL": "xinyuan5@staff.sina.com.cn",
    "work_position": "理想18层/西/6/4",
    "Contact_Phone": "0000",
    "cell_phone": "",
    "EMPLOYEE_ID": "202312",
    "job": "IOS开发工程师",
    "department_id": "100990",
    "deptname": "客户端技术开发部",
    "alias": null,
    "showflag": 1,
    "weibo": "5787473432",
    "ENGLISH_NAME": "Chai XinYuan"
}, {
    "rownumber": "2",
    "empName": "陈宝成",
    "EMAIL": "baocheng@staff.sina.com.cn",
    "work_position": "理想18层/西/2/3",
    "Contact_Phone": "6979",
    "cell_phone": "",
    "EMPLOYEE_ID": "14408",
    "job": "高级安卓开发工程师",
    "department_id": "100990",
    "deptname": "客户端技术开发部",
    "alias": null,
    "showflag": 1,
    "weibo": "5653197323",
    "ENGLISH_NAME": "CHEN BAOCHENG"
}, {
    "rownumber": "3",
    "empName": "董典辉",
    "EMAIL": "dianhui@staff.sina.com.cn",
    "work_position": null,
    "Contact_Phone": "6368",
    "cell_phone": "",
    "EMPLOYEE_ID": "14234",
    "job": "资深移动开发工程师",
    "department_id": "100990",
    "deptname": "客户端技术开发部",
    "alias": null,
    "showflag": 1,
    "weibo": "5652911934",
    "ENGLISH_NAME": "DONG DIANHUI"
}, {
    "rownumber": "4",
    "empName": "高华梅",
    "EMAIL": "huamei1@staff.sina.com.cn",
    "work_position": "理想18层/西/3/4",
    "Contact_Phone": "9871",
    "cell_phone": "",
    "EMPLOYEE_ID": "13606",
    "job": "安卓开发工程师",
    "department_id": "100990",
    "deptname": "客户端技术开发部",
    "alias": null,
    "showflag": 1,
    "weibo": "5652911956",
    "ENGLISH_NAME": "GAO HUAMEI"
}, {
    "rownumber": "5",
    "empName": "韩明豹",
    "EMAIL": "mingbao@staff.sina.com.cn",
    "work_position": null,
    "Contact_Phone": null,
    "cell_phone": "",
    "EMPLOYEE_ID": "201875",
    "job": "安卓开发工程师",
    "department_id": "100990",
    "deptname": "客户端技术开发部",
    "alias": null,
    "showflag": 1,
    "weibo": "5727251459",
    "ENGLISH_NAME": "Han Mingbao"
}, {
    "rownumber": "6",
    "empName": "韩耀东",
    "EMAIL": "yaodong1@staff.sina.com.cn",
    "work_position": null,
    "Contact_Phone": null,
    "cell_phone": "",
    "EMPLOYEE_ID": "201019",
    "job": "安卓开发工程师",
    "department_id": "100990",
    "deptname": "客户端技术开发部",
    "alias": null,
    "showflag": 1,
    "weibo": "1653882532",
    "ENGLISH_NAME": "han yaodong"
}, {
    "rownumber": "7",
    "empName": "及旭辉",
    "EMAIL": "xuhui3@staff.sina.com.cn",
    "work_position": "泰鹏6层///",
    "Contact_Phone": "9845",
    "cell_phone": "",
    "EMPLOYEE_ID": "13088",
    "job": "软件开发工程师",
    "department_id": "100990",
    "deptname": "客户端技术开发部",
    "alias": null,
    "showflag": 1,
    "weibo": "1636141841",
    "ENGLISH_NAME": "JI XUHUI"
}, {
    "rownumber": "8",
    "empName": "李盛",
    "EMAIL": "lisheng3@staff.sina.com.cn",
    "work_position": null,
    "Contact_Phone": null,
    "cell_phone": "",
    "EMPLOYEE_ID": "201742",
    "job": "IOS开发工程师",
    "department_id": "100990",
    "deptname": "客户端技术开发部",
    "alias": null,
    "showflag": 1,
    "weibo": "5708331262",
    "ENGLISH_NAME": "li sheng"
}, {
    "rownumber": "9",
    "empName": "刘欢",
    "EMAIL": "liuhuan@staff.sina.com.cn",
    "work_position": "理想18层/西/5/4",
    "Contact_Phone": "0000",
    "cell_phone": "",
    "EMPLOYEE_ID": "201779",
    "job": "IOS高级开发工程师",
    "department_id": "100990",
    "deptname": "客户端技术开发部",
    "alias": null,
    "showflag": 1,
    "weibo": "1814648827",
    "ENGLISH_NAME": "LIU HUAN"
}, {
    "rownumber": "10",
    "empName": "孙博",
    "EMAIL": "sunbo@staff.sina.com.cn",
    "work_position": "理想18层/西/5/1",
    "Contact_Phone": "5769",
    "cell_phone": "",
    "EMPLOYEE_ID": "13650",
    "job": "IOS开发工程师",
    "department_id": "100990",
    "deptname": "客户端技术开发部",
    "alias": null,
    "showflag": 1,
    "weibo": "2093596142",
    "ENGLISH_NAME": "SUN BO"
}, {
    "rownumber": "11",
    "empName": "王祥",
    "EMAIL": "wangxiang5@staff.sina.com.cn",
    "work_position": "理想18层/北/6/1",
    "Contact_Phone": "9858",
    "cell_phone": "",
    "EMPLOYEE_ID": "13037",
    "job": "高级IOS开发工程师",
    "department_id": "100990",
    "deptname": "客户端技术开发部",
    "alias": null,
    "showflag": 1,
    "weibo": "5653197344",
    "ENGLISH_NAME": "WANG XIANG"
}, {
    "rownumber": "12",
    "empName": "杨志新",
    "EMAIL": "zhixin3@staff.sina.com.cn",
    "work_position": null,
    "Contact_Phone": "6367",
    "cell_phone": "",
    "EMPLOYEE_ID": "14191",
    "job": "PHP开发工程师",
    "department_id": "100990",
    "deptname": "客户端技术开发部",
    "alias": null,
    "showflag": 1,
    "weibo": "5652911860",
    "ENGLISH_NAME": "YANG ZHIXIN"
}, {
    "rownumber": "13",
    "empName": "袁阳光",
    "EMAIL": "yangguang7@staff.sina.com.cn",
    "work_position": null,
    "Contact_Phone": "9876",
    "cell_phone": "",
    "EMPLOYEE_ID": "13775",
    "job": "IOS开发工程师",
    "department_id": "100990",
    "deptname": "客户端技术开发部",
    "alias": null,
    "showflag": 1,
    "weibo": "5652911952",
    "ENGLISH_NAME": "YUAN YANGGUANG"
}, {
    "rownumber": "14",
    "empName": "张聪辉",
    "EMAIL": "conghui1@staff.sina.com.cn",
    "work_position": "理想18层/西/2/4",
    "Contact_Phone": "6998",
    "cell_phone": "",
    "EMPLOYEE_ID": "12064",
    "job": "安卓开发工程师",
    "department_id": "100990",
    "deptname": "客户端技术开发部",
    "alias": null,
    "showflag": 1,
    "weibo": "5653197350",
    "ENGLISH_NAME": "ZHANG CONGHUI"
}, {
    "rownumber": "15",
    "empName": "周利彬",
    "EMAIL": "libin8@staff.sina.com.cn",
    "work_position": null,
    "Contact_Phone": "5610",
    "cell_phone": "",
    "EMPLOYEE_ID": "13425",
    "job": "安卓开发工程师",
    "department_id": "100990",
    "deptname": "客户端技术开发部",
    "alias": null,
    "showflag": 1,
    "weibo": "5652911955",
    "ENGLISH_NAME": "ZHOU LIBIN"
}, {
    "rownumber": "16",
    "empName": "朱良刚",
    "EMAIL": "lianggang@staff.sina.com.cn",
    "work_position": "理想18层/西//",
    "Contact_Phone": "5562",
    "cell_phone": "",
    "EMPLOYEE_ID": "13505",
    "job": "资深移动开发工程师",
    "department_id": "100990",
    "deptname": "客户端技术开发部",
    "alias": null,
    "showflag": 1,
    "weibo": "5652911957",
    "ENGLISH_NAME": "ZHU LIANGGANG"
}, {
    "rownumber": "17",
    "empName": "朱利明",
    "EMAIL": "liming20@staff.sina.com.cn",
    "work_position": "理想18层/西/5/5",
    "Contact_Phone": "9881",
    "cell_phone": "",
    "EMPLOYEE_ID": "14650",
    "job": "高级IOS开发工程师",
    "department_id": "100990",
    "deptname": "客户端技术开发部",
    "alias": null,
    "showflag": 1,
    "weibo": "5653197331",
    "ENGLISH_NAME": "ZHU LIMING"
}, {
    "rownumber": "18",
    "empName": "曹佳莹",
    "EMAIL": "jiaying6@staff.sina.com.cn",
    "work_position": null,
    "Contact_Phone": null,
    "cell_phone": "",
    "EMPLOYEE_ID": "201258",
    "job": "编辑",
    "department_id": "101167",
    "deptname": "内容运营部",
    "alias": null,
    "showflag": 1,
    "weibo": "5703433338",
    "ENGLISH_NAME": "Cao Jiaying"
}, {
    "rownumber": "19",
    "empName": "常新月",
    "EMAIL": "xinyue6@staff.sina.com.cn",
    "work_position": null,
    "Contact_Phone": null,
    "cell_phone": "",
    "EMPLOYEE_ID": "200791",
    "job": "编辑",
    "department_id": "101167",
    "deptname": "内容运营部",
    "alias": null,
    "showflag": 1,
    "weibo": "5652399445",
    "ENGLISH_NAME": "chang xinyue"
}, {
    "rownumber": "20",
    "empName": "陈琪斐",
    "EMAIL": "qifei1@staff.sina.com.cn",
    "work_position": "理想18层/北/5/7",
    "Contact_Phone": "5800",
    "cell_phone": "",
    "EMPLOYEE_ID": "9281",
    "job": "媒体运营",
    "department_id": "101167",
    "deptname": "内容运营部",
    "alias": null,
    "showflag": 1,
    "weibo": "5652690930",
    "ENGLISH_NAME": "CHEN QIFEI"
}, {
    "rownumber": "21",
    "empName": "程波",
    "EMAIL": "chengbo5@staff.sina.com.cn",
    "work_position": null,
    "Contact_Phone": null,
    "cell_phone": "",
    "EMPLOYEE_ID": "201911",
    "job": "编辑",
    "department_id": "101167",
    "deptname": "内容运营部",
    "alias": null,
    "showflag": 1,
    "weibo": "5727911234",
    "ENGLISH_NAME": "cheng bo"
}, {
    "rownumber": "22",
    "empName": "成龙",
    "EMAIL": "chenglong8@staff.sina.com.cn",
    "work_position": "理想18层/北/6/6",
    "Contact_Phone": "5134",
    "cell_phone": "",
    "EMPLOYEE_ID": "14416",
    "job": "高级编辑",
    "department_id": "101167",
    "deptname": "内容运营部",
    "alias": null,
    "showflag": 1,
    "weibo": "5652690951",
    "ENGLISH_NAME": "CHENG LONG"
}, {
    "rownumber": "23",
    "empName": "丛松",
    "EMAIL": "congsong@staff.sina.com.cn",
    "work_position": "理想18层/北/2/7",
    "Contact_Phone": "5453",
    "cell_phone": "",
    "EMPLOYEE_ID": "3613",
    "job": "主编",
    "department_id": "101167",
    "deptname": "内容运营部",
    "alias": null,
    "showflag": 1,
    "weibo": "1088791230",
    "ENGLISH_NAME": "CONG SONG"
}, {
    "rownumber": "24",
    "empName": "丁冰冰",
    "EMAIL": "bingbing3@staff.sina.com.cn",
    "work_position": "理想18层/西/10/1",
    "Contact_Phone": "6951",
    "cell_phone": "",
    "EMPLOYEE_ID": "14621",
    "job": "编辑",
    "department_id": "101167",
    "deptname": "内容运营部",
    "alias": null,
    "showflag": 1,
    "weibo": "5652690958",
    "ENGLISH_NAME": "DING BINGBING"
}, {
    "rownumber": "25",
    "empName": "范煜喆",
    "EMAIL": "fanyuzhe@staff.sina.com.cn",
    "work_position": "理想18层/东//",
    "Contact_Phone": "5899",
    "cell_phone": "",
    "EMPLOYEE_ID": "1705",
    "job": "编辑",
    "department_id": "101167",
    "deptname": "内容运营部",
    "alias": null,
    "showflag": 1,
    "weibo": "87204505",
    "ENGLISH_NAME": "FAN YUZHE"
}, {
    "rownumber": "26",
    "empName": "冯博",
    "EMAIL": "fengbo@staff.sina.com.cn",
    "work_position": "理想19层/东/13/7",
    "Contact_Phone": "5120",
    "cell_phone": "",
    "EMPLOYEE_ID": "2891",
    "job": "高级经理",
    "department_id": "101167",
    "deptname": "内容运营部",
    "alias": null,
    "showflag": 1,
    "weibo": "5652690937",
    "ENGLISH_NAME": "FENG BO"
}, {
    "rownumber": "27",
    "empName": "何英婷",
    "EMAIL": "yingting1@staff.sina.com.cn",
    "work_position": null,
    "Contact_Phone": null,
    "cell_phone": "",
    "EMPLOYEE_ID": "201075",
    "job": "编辑",
    "department_id": "101167",
    "deptname": "内容运营部",
    "alias": null,
    "showflag": 1,
    "weibo": "5703106388",
    "ENGLISH_NAME": "he yingting"
}, {
    "rownumber": "28",
    "empName": "雷晓燕",
    "EMAIL": "xiaoyan3@staff.sina.com.cn",
    "work_position": "理想18层/北/3/3",
    "Contact_Phone": "5578",
    "cell_phone": "",
    "EMPLOYEE_ID": "4543",
    "job": "高级产品运营经理",
    "department_id": "101167",
    "deptname": "内容运营部",
    "alias": null,
    "showflag": 1,
    "weibo": "5652399438",
    "ENGLISH_NAME": "LEI XIAOYAN"
}, {
    "rownumber": "29",
    "empName": "李娟",
    "EMAIL": "lijuan23@staff.sina.com.cn",
    "work_position": null,
    "Contact_Phone": null,
    "cell_phone": "",
    "EMPLOYEE_ID": "200829",
    "job": "编辑",
    "department_id": "101167",
    "deptname": "内容运营部",
    "alias": null,
    "showflag": 1,
    "weibo": "5652399443",
    "ENGLISH_NAME": "li juan"
}, {
    "rownumber": "30",
    "empName": "李晓波",
    "EMAIL": "xiaobo13@staff.sina.com.cn",
    "work_position": null,
    "Contact_Phone": "",
    "cell_phone": "",
    "EMPLOYEE_ID": "12068",
    "job": "编辑",
    "department_id": "101167",
    "deptname": "内容运营部",
    "alias": null,
    "showflag": 1,
    "weibo": "5652690940",
    "ENGLISH_NAME": "LI XIAOBO"
}, {
    "rownumber": "31",
    "empName": "刘皓",
    "EMAIL": "liuhao3@staff.sina.com.cn",
    "work_position": null,
    "Contact_Phone": "6608",
    "cell_phone": "",
    "EMPLOYEE_ID": "6865",
    "job": "编辑",
    "department_id": "101167",
    "deptname": "内容运营部",
    "alias": null,
    "showflag": 1,
    "weibo": "5652399435",
    "ENGLISH_NAME": "LIU HAO"
}, {
    "rownumber": "32",
    "empName": "刘佳",
    "EMAIL": "liujia16@staff.sina.com.cn",
    "work_position": null,
    "Contact_Phone": "5470",
    "cell_phone": "",
    "EMPLOYEE_ID": "14255",
    "job": "编辑",
    "department_id": "101167",
    "deptname": "内容运营部",
    "alias": null,
    "showflag": 1,
    "weibo": "5652690956",
    "ENGLISH_NAME": "LIU JIA"
}, {
    "rownumber": "33",
    "empName": "刘敬",
    "EMAIL": "liujing6@staff.sina.com.cn",
    "work_position": "理想18层/北/2/4",
    "Contact_Phone": "6529",
    "cell_phone": "",
    "EMPLOYEE_ID": "9717",
    "job": "高级编辑",
    "department_id": "101167",
    "deptname": "内容运营部",
    "alias": null,
    "showflag": 1,
    "weibo": "5652399434",
    "ENGLISH_NAME": "LIU JING"
}, {
    "rownumber": "34",
    "empName": "刘亚非",
    "EMAIL": "yafei5@staff.sina.com.cn",
    "work_position": "理想18层/北/4/1",
    "Contact_Phone": "5853",
    "cell_phone": "",
    "EMPLOYEE_ID": "201074",
    "job": "编辑",
    "department_id": "101167",
    "deptname": "内容运营部",
    "alias": null,
    "showflag": 1,
    "weibo": "2028810631",
    "ENGLISH_NAME": "Liu Yafei"
}, {
    "rownumber": "35",
    "empName": "马嫣然",
    "EMAIL": "yanran@staff.sina.com.cn",
    "work_position": "理想18层/北/3/7",
    "Contact_Phone": "5430",
    "cell_phone": "",
    "EMPLOYEE_ID": "7847",
    "job": "高级运营主管",
    "department_id": "101167",
    "deptname": "内容运营部",
    "alias": null,
    "showflag": 1,
    "weibo": "1642877311",
    "ENGLISH_NAME": "MA YANRAN"
}, {
    "rownumber": "36",
    "empName": "马轶凡",
    "EMAIL": "yifan9@staff.sina.com.cn",
    "work_position": "理想18层/北/5/3",
    "Contact_Phone": "5407",
    "cell_phone": "",
    "EMPLOYEE_ID": "15122",
    "job": "编辑",
    "department_id": "101167",
    "deptname": "内容运营部",
    "alias": null,
    "showflag": 1,
    "weibo": "1257508777",
    "ENGLISH_NAME": "ma yifan"
}, {
    "rownumber": "37",
    "empName": "钱英",
    "EMAIL": "qianying3@staff.sina.com.cn",
    "work_position": null,
    "Contact_Phone": null,
    "cell_phone": "",
    "EMPLOYEE_ID": "202432",
    "job": "编辑",
    "department_id": "101167",
    "deptname": "内容运营部",
    "alias": null,
    "showflag": 1,
    "weibo": "5803220376",
    "ENGLISH_NAME": "Qian Ying"
}, {
    "rownumber": "38",
    "empName": "宋瑞峰",
    "EMAIL": "ruifeng5@staff.sina.com.cn",
    "work_position": "理想18层/北/4/5",
    "Contact_Phone": "5296",
    "cell_phone": "",
    "EMPLOYEE_ID": "14743",
    "job": "编辑",
    "department_id": "101167",
    "deptname": "内容运营部",
    "alias": null,
    "showflag": 1,
    "weibo": "5652399452",
    "ENGLISH_NAME": "SONG RUIFENG"
}, {
    "rownumber": "39",
    "empName": "涂赛凤",
    "EMAIL": "saifeng@staff.sina.com.cn",
    "work_position": "理想18层/西/8/2",
    "Contact_Phone": "62676253",
    "cell_phone": "",
    "EMPLOYEE_ID": "201759",
    "job": "编辑",
    "department_id": "101167",
    "deptname": "内容运营部",
    "alias": null,
    "showflag": 1,
    "weibo": "5708014777",
    "ENGLISH_NAME": "Tu Saifeng"
}, {
    "rownumber": "40",
    "empName": "王佳楠",
    "EMAIL": "jianan5@staff.sina.com.cn",
    "work_position": "理想20层/东/9/8",
    "Contact_Phone": "5317",
    "cell_phone": "",
    "EMPLOYEE_ID": "14727",
    "job": "编辑",
    "department_id": "101167",
    "deptname": "内容运营部",
    "alias": null,
    "showflag": 1,
    "weibo": "1829961175",
    "ENGLISH_NAME": "WANG JIANAN"
}, {
    "rownumber": "41",
    "empName": "王强",
    "EMAIL": "wangqiang5@staff.sina.com.cn",
    "work_position": "理想18层/北/5/1",
    "Contact_Phone": "6983",
    "cell_phone": "",
    "EMPLOYEE_ID": "200360",
    "job": "编辑",
    "department_id": "101167",
    "deptname": "内容运营部",
    "alias": null,
    "showflag": 1,
    "weibo": "5652690943",
    "ENGLISH_NAME": "wang qiang"
}, {
    "rownumber": "42",
    "empName": "王瑶",
    "EMAIL": "wangyao1@staff.sina.com.cn",
    "work_position": null,
    "Contact_Phone": null,
    "cell_phone": "",
    "EMPLOYEE_ID": "201727",
    "job": "编辑",
    "department_id": "101167",
    "deptname": "内容运营部",
    "alias": null,
    "showflag": 1,
    "weibo": "5704803493",
    "ENGLISH_NAME": "wang yao"
}, {
    "rownumber": "43",
    "empName": "王云",
    "EMAIL": "wangyun@staff.sina.com.cn",
    "work_position": null,
    "Contact_Phone": "",
    "cell_phone": "",
    "EMPLOYEE_ID": "14686",
    "job": "编辑",
    "department_id": "101167",
    "deptname": "内容运营部",
    "alias": null,
    "showflag": 1,
    "weibo": "5652690959",
    "ENGLISH_NAME": "WANG YUN"
}, {
    "rownumber": "44",
    "empName": "魏冕",
    "EMAIL": "weimian@staff.sina.com.cn",
    "work_position": "理想18层/北/3/1",
    "Contact_Phone": "6680",
    "cell_phone": "",
    "EMPLOYEE_ID": "14417",
    "job": "高级编辑",
    "department_id": "101167",
    "deptname": "内容运营部",
    "alias": null,
    "showflag": 1,
    "weibo": "5652399447",
    "ENGLISH_NAME": "WEI MIAN"
}, {
    "rownumber": "45",
    "empName": "许玮",
    "EMAIL": "xuwei3@staff.sina.com.cn",
    "work_position": "理想20层/东/12/5",
    "Contact_Phone": "5728",
    "cell_phone": "",
    "EMPLOYEE_ID": "4970",
    "job": "内容经理",
    "department_id": "101167",
    "deptname": "内容运营部",
    "alias": null,
    "showflag": 1,
    "weibo": "1062683134",
    "ENGLISH_NAME": "XU WEI"
}, {
    "rownumber": "46",
    "empName": "姚昇",
    "EMAIL": "yaosheng@staff.sina.com.cn",
    "work_position": "理想18层/北/2/5",
    "Contact_Phone": "82244577",
    "cell_phone": "",
    "EMPLOYEE_ID": "200766",
    "job": "编辑",
    "department_id": "101167",
    "deptname": "内容运营部",
    "alias": null,
    "showflag": 1,
    "weibo": "5652685152",
    "ENGLISH_NAME": "yao sheng"
}, {
    "rownumber": "47",
    "empName": "殷婷婷",
    "EMAIL": "tingting16@staff.sina.com.cn",
    "work_position": "理想19层/北/5/1",
    "Contact_Phone": "6136",
    "cell_phone": "",
    "EMPLOYEE_ID": "7871",
    "job": "高级产品运营经理_I",
    "department_id": "101167",
    "deptname": "内容运营部",
    "alias": null,
    "showflag": 1,
    "weibo": "1462165315",
    "ENGLISH_NAME": "YIN TINGTING"
}, {
    "rownumber": "48",
    "empName": "于术佳",
    "EMAIL": "shujia1@staff.sina.com.cn",
    "work_position": null,
    "Contact_Phone": null,
    "cell_phone": "",
    "EMPLOYEE_ID": "201974",
    "job": "编辑",
    "department_id": "101167",
    "deptname": "内容运营部",
    "alias": null,
    "showflag": 1,
    "weibo": "5732572760",
    "ENGLISH_NAME": "Yu shujia"
}, {
    "rownumber": "49",
    "empName": "于怡航",
    "EMAIL": "yihang1@staff.sina.com.cn",
    "work_position": "理想18层/北/3/5",
    "Contact_Phone": "5786",
    "cell_phone": "",
    "EMPLOYEE_ID": "14275",
    "job": "原创编辑",
    "department_id": "101167",
    "deptname": "内容运营部",
    "alias": null,
    "showflag": 1,
    "weibo": "5652399448",
    "ENGLISH_NAME": "YU YIHANG"
}, {
    "rownumber": "50",
    "empName": "藏保锋",
    "EMAIL": "baofeng1@staff.sina.com.cn",
    "work_position": null,
    "Contact_Phone": "",
    "cell_phone": "",
    "EMPLOYEE_ID": "6833",
    "job": "编辑",
    "department_id": "101167",
    "deptname": "内容运营部",
    "alias": null,
    "showflag": 1,
    "weibo": "5652393741",
    "ENGLISH_NAME": "ZANG BAOFENG"
}, {
    "rownumber": "51",
    "empName": "周晓宇",
    "EMAIL": "xiaoyu23@staff.sina.com.cn",
    "work_position": "理想18层/北/3/2",
    "Contact_Phone": "6587",
    "cell_phone": "",
    "EMPLOYEE_ID": "14788",
    "job": "编辑",
    "department_id": "101167",
    "deptname": "内容运营部",
    "alias": null,
    "showflag": 1,
    "weibo": "5652399451",
    "ENGLISH_NAME": "ZHOU XIAOYU"
}, {
    "rownumber": "52",
    "empName": "迟子傲",
    "EMAIL": "ziao@staff.sina.com.cn",
    "work_position": null,
    "Contact_Phone": null,
    "cell_phone": "",
    "EMPLOYEE_ID": "202103",
    "job": "UI设计师",
    "department_id": "101166",
    "deptname": "手浪技术开发部",
    "alias": null,
    "showflag": 1,
    "weibo": "5747019984",
    "ENGLISH_NAME": "chi ziao"
}, {
    "rownumber": "53",
    "empName": "邓美玲",
    "EMAIL": "meiling3@staff.sina.com.cn",
    "work_position": "理想18层/西/9/1",
    "Contact_Phone": "6243",
    "cell_phone": "",
    "EMPLOYEE_ID": "14994",
    "job": "视觉设计师",
    "department_id": "101166",
    "deptname": "手浪技术开发部",
    "alias": null,
    "showflag": 1,
    "weibo": "1864725485",
    "ENGLISH_NAME": "DENG MEILING"
}, {
    "rownumber": "54",
    "empName": "段团辉",
    "EMAIL": "tuanhui@staff.sina.com.cn",
    "work_position": "理想20层/东/6/3",
    "Contact_Phone": "5044",
    "cell_phone": "",
    "EMPLOYEE_ID": "13685",
    "job": "高级软件开发工程师",
    "department_id": "101166",
    "deptname": "手浪技术开发部",
    "alias": null,
    "showflag": 1,
    "weibo": "5652685132",
    "ENGLISH_NAME": "DUAN TUANHUI"
}, {
    "rownumber": "55",
    "empName": "高峰",
    "EMAIL": "gaofeng1@staff.sina.com.cn",
    "work_position": "泰鹏6层/西/12/3",
    "Contact_Phone": "5243",
    "cell_phone": "",
    "EMPLOYEE_ID": "5171",
    "job": "视觉设计经理",
    "department_id": "101166",
    "deptname": "手浪技术开发部",
    "alias": null,
    "showflag": 1,
    "weibo": "1644686384",
    "ENGLISH_NAME": "GAO FENG"
}, {
    "rownumber": "56",
    "empName": "高鋆",
    "EMAIL": "gaoyun@staff.sina.com.cn",
    "work_position": null,
    "Contact_Phone": "5893",
    "cell_phone": "",
    "EMPLOYEE_ID": "7919",
    "job": "视觉设计师",
    "department_id": "101166",
    "deptname": "手浪技术开发部",
    "alias": null,
    "showflag": 1,
    "weibo": "5653197309",
    "ENGLISH_NAME": "GAO YUN"
}, {
    "rownumber": "57",
    "empName": "耿茜",
    "EMAIL": "gengxi@staff.sina.com.cn",
    "work_position": "理想18层/西/7/4",
    "Contact_Phone": "5458",
    "cell_phone": "",
    "EMPLOYEE_ID": "9423",
    "job": "视觉设计师",
    "department_id": "101166",
    "deptname": "手浪技术开发部",
    "alias": null,
    "showflag": 1,
    "weibo": "1770222535",
    "ENGLISH_NAME": "geng xi"
}, {
    "rownumber": "58",
    "empName": "谷杨",
    "EMAIL": "guyang@staff.sina.com.cn",
    "work_position": "朔黄8层/南//",
    "Contact_Phone": "",
    "cell_phone": "",
    "EMPLOYEE_ID": "14144",
    "job": "用户体验与设计高级主管",
    "department_id": "101166",
    "deptname": "手浪技术开发部",
    "alias": null,
    "showflag": 1,
    "weibo": "5652687120",
    "ENGLISH_NAME": "GU YANG"
}, {
    "rownumber": "59",
    "empName": "郭宁",
    "EMAIL": "guoning1@staff.sina.com.cn",
    "work_position": "理想18层/西//",
    "Contact_Phone": "2503",
    "cell_phone": "",
    "EMPLOYEE_ID": "13592",
    "job": "PHP开发工程师",
    "department_id": "101166",
    "deptname": "手浪技术开发部",
    "alias": null,
    "showflag": 1,
    "weibo": "5652393359",
    "ENGLISH_NAME": "GUO NING"
}, {
    "rownumber": "60",
    "empName": "贺海鹏",
    "EMAIL": "haipeng4@staff.sina.com.cn",
    "work_position": "理想20层/东/4/5",
    "Contact_Phone": "4416",
    "cell_phone": "",
    "EMPLOYEE_ID": "12061",
    "job": "PHP开发工程师",
    "department_id": "101166",
    "deptname": "手浪技术开发部",
    "alias": null,
    "showflag": 1,
    "weibo": "5652685126",
    "ENGLISH_NAME": "HE HAIPENG"
}, {
    "rownumber": "61",
    "empName": "禾文汇",
    "EMAIL": "wenhui12@staff.sina.com.cn",
    "work_position": "理想20层/北/6/2",
    "Contact_Phone": "4599",
    "cell_phone": "",
    "EMPLOYEE_ID": "200453",
    "job": "数据分析师",
    "department_id": "101166",
    "deptname": "手浪技术开发部",
    "alias": null,
    "showflag": 1,
    "weibo": "5652393733",
    "ENGLISH_NAME": "He WenHui"
}, {
    "rownumber": "62",
    "empName": "何远锋",
    "EMAIL": "yuanfeng@staff.sina.com.cn",
    "work_position": "理想20层/东/9/1",
    "Contact_Phone": "3886",
    "cell_phone": "",
    "EMPLOYEE_ID": "15193",
    "job": "前端开发工程师",
    "department_id": "101166",
    "deptname": "手浪技术开发部",
    "alias": null,
    "showflag": 1,
    "weibo": "5652685135",
    "ENGLISH_NAME": "he yuanfeng"
}, {
    "rownumber": "63",
    "empName": "贾艳清",
    "EMAIL": "yanqing8@staff.sina.com.cn",
    "work_position": "理想20层/东/10/1",
    "Contact_Phone": "5142",
    "cell_phone": "",
    "EMPLOYEE_ID": "12871",
    "job": "设计师",
    "department_id": "101166",
    "deptname": "手浪技术开发部",
    "alias": null,
    "showflag": 1,
    "weibo": "1558524664",
    "ENGLISH_NAME": "JIA YANQING"
}, {
    "rownumber": "64",
    "empName": "江海强",
    "EMAIL": "haiqiang3@staff.sina.com.cn",
    "work_position": "理想18层/西/7/1",
    "Contact_Phone": "58593980",
    "cell_phone": "",
    "EMPLOYEE_ID": "202181",
    "job": "UI设计师",
    "department_id": "101166",
    "deptname": "手浪技术开发部",
    "alias": null,
    "showflag": 1,
    "weibo": "5764853258",
    "ENGLISH_NAME": "jiang haiqiang"
}, {
    "rownumber": "65",
    "empName": "李海阳",
    "EMAIL": "haiyang6@staff.sina.com.cn",
    "work_position": "理想18层/西/1/6",
    "Contact_Phone": "82244257",
    "cell_phone": "",
    "EMPLOYEE_ID": "200483",
    "job": "前端开发工程师",
    "department_id": "101166",
    "deptname": "手浪技术开发部",
    "alias": null,
    "showflag": 1,
    "weibo": "5652685145",
    "ENGLISH_NAME": "li haiyang"
}, {
    "rownumber": "66",
    "empName": "李爽",
    "EMAIL": "lishuang6@staff.sina.com.cn",
    "work_position": null,
    "Contact_Phone": "5632",
    "cell_phone": "",
    "EMPLOYEE_ID": "15047",
    "job": "交互设计师",
    "department_id": "101166",
    "deptname": "手浪技术开发部",
    "alias": null,
    "showflag": 1,
    "weibo": "5653197314",
    "ENGLISH_NAME": "LI SHUANG"
}, {
    "rownumber": "67",
    "empName": "李婷领",
    "EMAIL": "tingling@staff.sina.com.cn",
    "work_position": "理想20层/东/10/6",
    "Contact_Phone": "5825",
    "cell_phone": "",
    "EMPLOYEE_ID": "14528",
    "job": "前端开发工程师",
    "department_id": "101166",
    "deptname": "手浪技术开发部",
    "alias": null,
    "showflag": 1,
    "weibo": "2143409933",
    "ENGLISH_NAME": "LI TINGLING"
}, {
    "rownumber": "68",
    "empName": "梁瑞乐",
    "EMAIL": "ruile@staff.sina.com.cn",
    "work_position": null,
    "Contact_Phone": null,
    "cell_phone": "",
    "EMPLOYEE_ID": "200913",
    "job": "初级前端开发工程师",
    "department_id": "101166",
    "deptname": "手浪技术开发部",
    "alias": null,
    "showflag": 1,
    "weibo": "5652685148",
    "ENGLISH_NAME": "liang ruile"
}, {
    "rownumber": "69",
    "empName": "刘亮亮",
    "EMAIL": "liangliang12@staff.sina.com.cn",
    "work_position": null,
    "Contact_Phone": null,
    "cell_phone": "",
    "EMPLOYEE_ID": "200272",
    "job": "高级软件开发工程师",
    "department_id": "101166",
    "deptname": "手浪技术开发部",
    "alias": null,
    "showflag": 1,
    "weibo": "5652685138",
    "ENGLISH_NAME": "liu liangliang"
}, {
    "rownumber": "70",
    "empName": "刘庆",
    "EMAIL": "liuqing3@staff.sina.com.cn",
    "work_position": "理想20层/东/3/3",
    "Contact_Phone": "6342",
    "cell_phone": "",
    "EMPLOYEE_ID": "13828",
    "job": "PHP开发工程师",
    "department_id": "101166",
    "deptname": "手浪技术开发部",
    "alias": null,
    "showflag": 1,
    "weibo": "2402851787",
    "ENGLISH_NAME": "LIU QING"
}, {
    "rownumber": "71",
    "empName": "刘松涛",
    "EMAIL": "songtao7@staff.sina.com.cn",
    "work_position": "理想20层/东/8/7",
    "Contact_Phone": "6180",
    "cell_phone": "",
    "EMPLOYEE_ID": "13073",
    "job": "技术副总监",
    "department_id": "101166",
    "deptname": "手浪技术开发部",
    "alias": null,
    "showflag": 1,
    "weibo": "5652685128",
    "ENGLISH_NAME": "LIU SONGTAO"
}, {
    "rownumber": "72",
    "empName": "刘献芳",
    "EMAIL": "xianfang5@staff.sina.com.cn",
    "work_position": null,
    "Contact_Phone": "5481",
    "cell_phone": "",
    "EMPLOYEE_ID": "13006",
    "job": "高级设计师",
    "department_id": "101166",
    "deptname": "手浪技术开发部",
    "alias": null,
    "showflag": 1,
    "weibo": "5652911912",
    "ENGLISH_NAME": "LIU XIANFANG"
}, {
    "rownumber": "73",
    "empName": "骆也",
    "EMAIL": "luoye@staff.sina.com.cn",
    "work_position": null,
    "Contact_Phone": null,
    "cell_phone": "",
    "EMPLOYEE_ID": "202074",
    "job": "前端开发工程师",
    "department_id": "101166",
    "deptname": "手浪技术开发部",
    "alias": null,
    "showflag": 1,
    "weibo": "5745355530",
    "ENGLISH_NAME": "luo ye"
}, {
    "rownumber": "74",
    "empName": "罗仲凯",
    "EMAIL": "zhongkai@staff.sina.com.cn",
    "work_position": "理想20层/东/4/4",
    "Contact_Phone": "5739",
    "cell_phone": "",
    "EMPLOYEE_ID": "201713",
    "job": "PHP开发工程师",
    "department_id": "101166",
    "deptname": "手浪技术开发部",
    "alias": null,
    "showflag": 1,
    "weibo": "5704803486",
    "ENGLISH_NAME": "luo zhongkai"
}, {
    "rownumber": "75",
    "empName": "牛猛",
    "EMAIL": "niumeng@staff.sina.com.cn",
    "work_position": "理想18层/西/1/2",
    "Contact_Phone": "82244861",
    "cell_phone": "",
    "EMPLOYEE_ID": "200047",
    "job": "前端开发工程师",
    "department_id": "101166",
    "deptname": "手浪技术开发部",
    "alias": null,
    "showflag": 1,
    "weibo": "5652393728",
    "ENGLISH_NAME": "Niu Meng"
}, {
    "rownumber": "76",
    "empName": "师帅",
    "EMAIL": "shishuai1@staff.sina.com.cn",
    "work_position": "理想20层/东//",
    "Contact_Phone": "5751",
    "cell_phone": "",
    "EMPLOYEE_ID": "200545",
    "job": "PHP开发工程师",
    "department_id": "101166",
    "deptname": "手浪技术开发部",
    "alias": null,
    "showflag": 1,
    "weibo": "1939379867",
    "ENGLISH_NAME": "shi shuai"
}, {
    "rownumber": "77",
    "empName": "孙庆利",
    "EMAIL": "qingli1@staff.sina.com.cn",
    "work_position": "理想20层/东/6/4",
    "Contact_Phone": "4256",
    "cell_phone": "",
    "EMPLOYEE_ID": "21755",
    "job": "高级软件开发工程师",
    "department_id": "101166",
    "deptname": "手浪技术开发部",
    "alias": null,
    "showflag": 1,
    "weibo": "2169266771",
    "ENGLISH_NAME": "SUN QINGLI"
}, {
    "rownumber": "78",
    "empName": "张昱东",
    "EMAIL": "yudong4@staff.sina.com.cn",
    "work_position": "理想18层/西/+1/1",
    "Contact_Phone": "5116",
    "cell_phone": "",
    "EMPLOYEE_ID": "11522",
    "job": "PHP开发工程师",
    "department_id": "101166",
    "deptname": "手浪技术开发部",
    "alias": null,
    "showflag": 1,
    "weibo": "5652685122",
    "ENGLISH_NAME": "SUN YUDONG"
}, {
    "rownumber": "79",
    "empName": "铁铮",
    "EMAIL": "tiezheng@staff.sina.com.cn",
    "work_position": "理想18层/西/2/7",
    "Contact_Phone": "5793",
    "cell_phone": "",
    "EMPLOYEE_ID": "7570",
    "job": "数据分析师",
    "department_id": "101166",
    "deptname": "手浪技术开发部",
    "alias": null,
    "showflag": 1,
    "weibo": "1706415707",
    "ENGLISH_NAME": "TIE ZHENG"
}, {
    "rownumber": "80",
    "empName": "王永航",
    "EMAIL": "yonghang@staff.sina.com.cn",
    "work_position": "理想18层/东/1/1",
    "Contact_Phone": "6034",
    "cell_phone": "",
    "EMPLOYEE_ID": "202267",
    "job": "PHP开发工程师",
    "department_id": "101166",
    "deptname": "手浪技术开发部",
    "alias": null,
    "showflag": 1,
    "weibo": "5778591698",
    "ENGLISH_NAME": "wang yonghang"
}, {
    "rownumber": "81",
    "empName": "夏荻",
    "EMAIL": "xiadi@staff.sina.com.cn",
    "work_position": "理想18层/西/8/5",
    "Contact_Phone": "5872",
    "cell_phone": "",
    "EMPLOYEE_ID": "14402",
    "job": "交互设计师",
    "department_id": "101166",
    "deptname": "手浪技术开发部",
    "alias": null,
    "showflag": 1,
    "weibo": "5653197320",
    "ENGLISH_NAME": "XIA DI"
}, {
    "rownumber": "82",
    "empName": "薛昊",
    "EMAIL": "xuehao1@staff.sina.com.cn",
    "work_position": "泰鹏6层/西/10/3",
    "Contact_Phone": "2396",
    "cell_phone": "",
    "EMPLOYEE_ID": "9383",
    "job": "视觉设计师",
    "department_id": "101166",
    "deptname": "手浪技术开发部",
    "alias": null,
    "showflag": 1,
    "weibo": "5699316444",
    "ENGLISH_NAME": "XUE HAO"
}, {
    "rownumber": "83",
    "empName": "袁远",
    "EMAIL": "yuanyuan23@staff.sina.com.cn",
    "work_position": "理想18层/西/1/4",
    "Contact_Phone": "5759",
    "cell_phone": "",
    "EMPLOYEE_ID": "13338",
    "job": "软件开发工程师",
    "department_id": "101166",
    "deptname": "手浪技术开发部",
    "alias": null,
    "showflag": 1,
    "weibo": "5652393721",
    "ENGLISH_NAME": "YUAN YUAN"
}, {
    "rownumber": "84",
    "empName": "张封宛",
    "EMAIL": "fengwan@staff.sina.com.cn",
    "work_position": null,
    "Contact_Phone": null,
    "cell_phone": "",
    "EMPLOYEE_ID": "202207",
    "job": "前端开发工程师",
    "department_id": "101166",
    "deptname": "手浪技术开发部",
    "alias": null,
    "showflag": 1,
    "weibo": "5766659576",
    "ENGLISH_NAME": "zhang fengwan"
}, {
    "rownumber": "85",
    "empName": "张洁",
    "EMAIL": "zhangjie10@staff.sina.com.cn",
    "work_position": null,
    "Contact_Phone": "3858",
    "cell_phone": "",
    "EMPLOYEE_ID": "13778",
    "job": "UI设计师",
    "department_id": "101166",
    "deptname": "手浪技术开发部",
    "alias": null,
    "showflag": 1,
    "weibo": "5652911910",
    "ENGLISH_NAME": "ZHANG JIE"
}, {
    "rownumber": "86",
    "empName": "张晶磊",
    "EMAIL": "jinglei@staff.sina.com.cn",
    "work_position": "理想20层/东/10/5",
    "Contact_Phone": "2067",
    "cell_phone": "",
    "EMPLOYEE_ID": "21138",
    "job": "页面架构工程师",
    "department_id": "101166",
    "deptname": "手浪技术开发部",
    "alias": null,
    "showflag": 1,
    "weibo": "5652685133",
    "ENGLISH_NAME": "ZHANG JINGLEI"
}, {
    "rownumber": "87",
    "empName": "张志强",
    "EMAIL": "zhiqiang18@staff.sina.com.cn",
    "work_position": "理想20层/东/2/3",
    "Contact_Phone": "5172",
    "cell_phone": "",
    "EMPLOYEE_ID": "12730",
    "job": "高级技术主管",
    "department_id": "101166",
    "deptname": "手浪技术开发部",
    "alias": null,
    "showflag": 1,
    "weibo": "1671051811",
    "ENGLISH_NAME": "ZHANG ZHIQIANG"
}, {
    "rownumber": "88",
    "empName": "赵欢欢",
    "EMAIL": "huanhuan5@staff.sina.com.cn",
    "work_position": "理想18层/西/+2/1",
    "Contact_Phone": "6980",
    "cell_phone": "",
    "EMPLOYEE_ID": "14455",
    "job": "PHP应用开发工程师",
    "department_id": "101166",
    "deptname": "手浪技术开发部",
    "alias": null,
    "showflag": 1,
    "weibo": "5652393738",
    "ENGLISH_NAME": "ZHAO HUANHUAN"
}, {
    "rownumber": "89",
    "empName": "郑炜",
    "EMAIL": "zhengwei9@staff.sina.com.cn",
    "work_position": "理想18层/西/5/7",
    "Contact_Phone": "5467",
    "cell_phone": "",
    "EMPLOYEE_ID": "14993",
    "job": "交互主管",
    "department_id": "101166",
    "deptname": "手浪技术开发部",
    "alias": null,
    "showflag": 1,
    "weibo": "5652911920",
    "ENGLISH_NAME": "ZHENG WEI"
}, {
    "rownumber": "90",
    "empName": "周晶",
    "EMAIL": "zhoujing2@staff.sina.com.cn",
    "work_position": "理想20层/东/5/3",
    "Contact_Phone": "3343",
    "cell_phone": "",
    "EMPLOYEE_ID": "21723",
    "job": "高级软件开发工程师",
    "department_id": "101166",
    "deptname": "手浪技术开发部",
    "alias": null,
    "showflag": 1,
    "weibo": "2237295867",
    "ENGLISH_NAME": "ZHOU JING"
}, {
    "rownumber": "91",
    "empName": "周璟",
    "EMAIL": "zhoujing1@staff.sina.com.cn",
    "work_position": "理想18层/西/9/6",
    "Contact_Phone": "4342",
    "cell_phone": "",
    "EMPLOYEE_ID": "8728",
    "job": "视觉设计师",
    "department_id": "101166",
    "deptname": "手浪技术开发部",
    "alias": null,
    "showflag": 1,
    "weibo": "1087523150",
    "ENGLISH_NAME": "ZHOU JING"
}, {
    "rownumber": "92",
    "empName": "范哲文",
    "EMAIL": "zhewen@staff.sina.com.cn",
    "work_position": "理想18层/西/5/6",
    "Contact_Phone": "9844",
    "cell_phone": "",
    "EMPLOYEE_ID": "13075",
    "job": "产品经理",
    "department_id": "100989",
    "deptname": "移动端产品部",
    "alias": null,
    "showflag": 1,
    "weibo": "1807454131",
    "ENGLISH_NAME": "FAN ZHEWEN"
}, {
    "rownumber": "93",
    "empName": "韩雨辰",
    "EMAIL": "yuchen5@staff.sina.com.cn",
    "work_position": "理想18层/西/10/1",
    "Contact_Phone": "6944",
    "cell_phone": "",
    "EMPLOYEE_ID": "12757",
    "job": "媒体对接",
    "department_id": "100989",
    "deptname": "移动端产品部",
    "alias": null,
    "showflag": 1,
    "weibo": "2464984217",
    "ENGLISH_NAME": "HAN YUCHEN"
}, {
    "rownumber": "94",
    "empName": "李根",
    "EMAIL": "ligen@staff.sina.com.cn",
    "work_position": "/东/1/1",
    "Contact_Phone": "9834",
    "cell_phone": "",
    "EMPLOYEE_ID": "11923",
    "job": "高级产品经理_I",
    "department_id": "100989",
    "deptname": "移动端产品部",
    "alias": null,
    "showflag": 1,
    "weibo": "5652911907",
    "ENGLISH_NAME": "LI GEN"
}, {
    "rownumber": "95",
    "empName": "李佳迅",
    "EMAIL": "jiaxun3@staff.sina.com.cn",
    "work_position": "理想18层/西/4/2",
    "Contact_Phone": "6910",
    "cell_phone": "",
    "EMPLOYEE_ID": "14121",
    "job": "产品经理",
    "department_id": "100989",
    "deptname": "移动端产品部",
    "alias": null,
    "showflag": 1,
    "weibo": "2370899741",
    "ENGLISH_NAME": "LI JIAXUN"
}, {
    "rownumber": "96",
    "empName": "李茜",
    "EMAIL": "lixi13@staff.sina.com.cn",
    "work_position": "理想18层/西/4/3",
    "Contact_Phone": "9835",
    "cell_phone": "",
    "EMPLOYEE_ID": "11449",
    "job": "高级产品经理_I",
    "department_id": "100989",
    "deptname": "移动端产品部",
    "alias": null,
    "showflag": 1,
    "weibo": "5652911909",
    "ENGLISH_NAME": "LI XI"
}, {
    "rownumber": "97",
    "empName": "刘琳",
    "EMAIL": "liulin6@staff.sina.com.cn",
    "work_position": "理想18层/西/9/4",
    "Contact_Phone": "3948",
    "cell_phone": "",
    "EMPLOYEE_ID": "200689",
    "job": "产品经理",
    "department_id": "100989",
    "deptname": "移动端产品部",
    "alias": null,
    "showflag": 1,
    "weibo": "1889864921",
    "ENGLISH_NAME": "liu lin"
}, {
    "rownumber": "98",
    "empName": "刘梦",
    "EMAIL": "liumeng1@staff.sina.com.cn",
    "work_position": "理想18层/西/9/2",
    "Contact_Phone": "5314",
    "cell_phone": "",
    "EMPLOYEE_ID": "12108",
    "job": "产品经理",
    "department_id": "100989",
    "deptname": "移动端产品部",
    "alias": null,
    "showflag": 1,
    "weibo": "5652911908",
    "ENGLISH_NAME": "LIU MENG"
}, {
    "rownumber": "99",
    "empName": "刘瑞",
    "EMAIL": "liurui3@staff.sina.com.cn",
    "work_position": null,
    "Contact_Phone": "9852",
    "cell_phone": "",
    "EMPLOYEE_ID": "13201",
    "job": "产品经理",
    "department_id": "100989",
    "deptname": "移动端产品部",
    "alias": null,
    "showflag": 1,
    "weibo": "5653197304",
    "ENGLISH_NAME": "LIU RUI"
}, {
    "rownumber": "100",
    "empName": "吕竞博",
    "EMAIL": "jingbo9@staff.sina.com.cn",
    "work_position": "理想18层/西/7/5",
    "Contact_Phone": "4997",
    "cell_phone": "",
    "EMPLOYEE_ID": "7393",
    "job": "产品经理",
    "department_id": "100989",
    "deptname": "移动端产品部",
    "alias": null,
    "showflag": 1,
    "weibo": "1682301902",
    "ENGLISH_NAME": "LV JINGBO"
}, {
    "rownumber": "101",
    "empName": "史嵘",
    "EMAIL": "shirong@staff.sina.com.cn",
    "work_position": "理想18层/西/4/1",
    "Contact_Phone": "4879",
    "cell_phone": "",
    "EMPLOYEE_ID": "201778",
    "job": "高级数据分析师",
    "department_id": "100989",
    "deptname": "移动端产品部",
    "alias": null,
    "showflag": 1,
    "weibo": "5727906668",
    "ENGLISH_NAME": "shi rong"
}, {
    "rownumber": "102",
    "empName": "石英杰",
    "EMAIL": "yingjie1@staff.sina.com.cn",
    "work_position": "泰鹏6层/北/14/24",
    "Contact_Phone": "9856",
    "cell_phone": "",
    "EMPLOYEE_ID": "4035",
    "job": "新浪财经客户端-高级产品经理",
    "department_id": "100989",
    "deptname": "移动端产品部",
    "alias": null,
    "showflag": 1,
    "weibo": "2296241781",
    "ENGLISH_NAME": "SHI YINGJIE"
}, {
    "rownumber": "103",
    "empName": "王焕斌",
    "EMAIL": "huanbin@staff.sina.com.cn",
    "work_position": null,
    "Contact_Phone": null,
    "cell_phone": "",
    "EMPLOYEE_ID": "202201",
    "job": "产品经理",
    "department_id": "100989",
    "deptname": "移动端产品部",
    "alias": null,
    "showflag": 1,
    "weibo": "5770883540",
    "ENGLISH_NAME": "wang huanbin"
}, {
    "rownumber": "104",
    "empName": "王磊",
    "EMAIL": "wanglei22@staff.sina.com.cn",
    "work_position": "理想19层/南/6/1",
    "Contact_Phone": "6182",
    "cell_phone": "",
    "EMPLOYEE_ID": "13295",
    "job": "产品经理",
    "department_id": "100989",
    "deptname": "移动端产品部",
    "alias": null,
    "showflag": 1,
    "weibo": "5652690393",
    "ENGLISH_NAME": "WANG LEI"
}, {
    "rownumber": "105",
    "empName": "夏春梅",
    "EMAIL": "chunmei5@staff.sina.com.cn",
    "work_position": "理想20层/东//",
    "Contact_Phone": "5291",
    "cell_phone": "",
    "EMPLOYEE_ID": "14593",
    "job": "产品经理",
    "department_id": "100989",
    "deptname": "移动端产品部",
    "alias": null,
    "showflag": 1,
    "weibo": "5652911927",
    "ENGLISH_NAME": "XIA CHUNMEI"
}, {
    "rownumber": "106",
    "empName": "杨芳",
    "EMAIL": "yangfang1@staff.sina.com.cn",
    "work_position": "泰鹏6层/北/15/13",
    "Contact_Phone": "9838",
    "cell_phone": "",
    "EMPLOYEE_ID": "21133",
    "job": "产品经理_II",
    "department_id": "100989",
    "deptname": "移动端产品部",
    "alias": null,
    "showflag": 1,
    "weibo": "5653197311",
    "ENGLISH_NAME": "YANG FANG"
}, {
    "rownumber": "107",
    "empName": "徐烨",
    "EMAIL": "xuye1@staff.sina.com.cn",
    "work_position": "理想20层/东//",
    "Contact_Phone": "-",
    "cell_phone": "",
    "EMPLOYEE_ID": "14877",
    "job": "产品经理",
    "department_id": "100989",
    "deptname": "移动端产品部",
    "alias": null,
    "showflag": 1,
    "weibo": "5652918305",
    "ENGLISH_NAME": "YU YE"
}, {
    "rownumber": "108",
    "empName": "董华",
    "EMAIL": "donghua5@staff.sina.com.cn",
    "work_position": "理想18层/北/25/2",
    "Contact_Phone": "010-62675452",
    "cell_phone": "",
    "EMPLOYEE_ID": "202075",
    "job": "资源运营",
    "department_id": "101168",
    "deptname": "移动渠道部",
    "alias": null,
    "showflag": 1,
    "weibo": "5745355533",
    "ENGLISH_NAME": "Dong Hua"
}, {
    "rownumber": "109",
    "empName": "黄凰",
    "EMAIL": "huanghuang@staff.sina.com.cn",
    "work_position": "理想18层/北/24/5",
    "Contact_Phone": "6833",
    "cell_phone": "",
    "EMPLOYEE_ID": "5238",
    "job": "编辑",
    "department_id": "101168",
    "deptname": "移动渠道部",
    "alias": null,
    "showflag": 1,
    "weibo": "5652917885",
    "ENGLISH_NAME": "HUANG HUANG"
}, {
    "rownumber": "110",
    "empName": "李娟娟",
    "EMAIL": "juanjuan5@staff.sina.com.cn",
    "work_position": "理想18层/北/23/6",
    "Contact_Phone": "4258",
    "cell_phone": "",
    "EMPLOYEE_ID": "13555",
    "job": "渠道运营主管",
    "department_id": "101168",
    "deptname": "移动渠道部",
    "alias": null,
    "showflag": 1,
    "weibo": "5653203205",
    "ENGLISH_NAME": "LI JUANJUAN"
}, {
    "rownumber": "111",
    "empName": "师帅",
    "EMAIL": "shishuai3@staff.sina.com.cn",
    "work_position": null,
    "Contact_Phone": null,
    "cell_phone": "",
    "EMPLOYEE_ID": "201008",
    "job": "渠道推广经理",
    "department_id": "101168",
    "deptname": "移动渠道部",
    "alias": null,
    "showflag": 1,
    "weibo": "5652917889",
    "ENGLISH_NAME": "SHI SHUAI"
}, {
    "rownumber": "112",
    "empName": "王泽峰",
    "EMAIL": "zefeng3@staff.sina.com.cn",
    "work_position": "理想18层/北/25/5",
    "Contact_Phone": "5828",
    "cell_phone": "",
    "EMPLOYEE_ID": "20361",
    "job": "渠道总监",
    "department_id": "101168",
    "deptname": "移动渠道部",
    "alias": null,
    "showflag": 1,
    "weibo": "5652393745",
    "ENGLISH_NAME": "WANG ZEFENG"
}, {
    "rownumber": "113",
    "empName": "王紫华",
    "EMAIL": "zihua1@staff.sina.com.cn",
    "work_position": "理想18层/北/26/4",
    "Contact_Phone": "6801",
    "cell_phone": "",
    "EMPLOYEE_ID": "201785",
    "job": "渠道拓展经理",
    "department_id": "101168",
    "deptname": "移动渠道部",
    "alias": null,
    "showflag": 1,
    "weibo": "1652117541",
    "ENGLISH_NAME": "wang zihua"
}, {
    "rownumber": "114",
    "empName": "于涓",
    "EMAIL": "yujuan1@staff.sina.com.cn",
    "work_position": "理想18层/北/23/5",
    "Contact_Phone": "6512",
    "cell_phone": "",
    "EMPLOYEE_ID": "14565",
    "job": "营销策划经理",
    "department_id": "101168",
    "deptname": "移动渠道部",
    "alias": null,
    "showflag": 1,
    "weibo": "5652917892",
    "ENGLISH_NAME": "YU JUAN"
}, {
    "rownumber": "115",
    "empName": "张皓",
    "EMAIL": "zhanghao12@staff.sina.com.cn",
    "work_position": null,
    "Contact_Phone": "",
    "cell_phone": "",
    "EMPLOYEE_ID": "21232",
    "job": "高级渠道拓展经理",
    "department_id": "101168",
    "deptname": "移动渠道部",
    "alias": null,
    "showflag": 1,
    "weibo": "5727906657",
    "ENGLISH_NAME": "ZHANG HAO"
}, {
    "rownumber": "116",
    "empName": "赵林宜",
    "EMAIL": "linyi3@staff.sina.com.cn",
    "work_position": "理想18层/北/7/3",
    "Contact_Phone": "13269200377",
    "cell_phone": "",
    "EMPLOYEE_ID": "201261",
    "job": "助理运营经理",
    "department_id": "101168",
    "deptname": "移动渠道部",
    "alias": null,
    "showflag": 1,
    "weibo": "5703109752",
    "ENGLISH_NAME": "zhao linyi"
}, {
    "rownumber": "117",
    "empName": "曹青梅",
    "EMAIL": "qingmei@staff.sina.com.cn",
    "work_position": null,
    "Contact_Phone": null,
    "cell_phone": "",
    "EMPLOYEE_ID": "201277",
    "job": "品牌管理",
    "department_id": "101169",
    "deptname": "移动市场部",
    "alias": null,
    "showflag": 1,
    "weibo": "1809231741",
    "ENGLISH_NAME": "cao qingmei"
}, {
    "rownumber": "118",
    "empName": "方茜",
    "EMAIL": "fangqian1@staff.sina.com.cn",
    "work_position": "理想18层/西/11/3",
    "Contact_Phone": "6408",
    "cell_phone": "",
    "EMPLOYEE_ID": "15046",
    "job": "BD项目经理",
    "department_id": "101169",
    "deptname": "移动市场部",
    "alias": null,
    "showflag": 1,
    "weibo": "5652393754",
    "ENGLISH_NAME": "FANG QIAN"
}, {
    "rownumber": "119",
    "empName": "侯爽",
    "EMAIL": "houshuang@staff.sina.com.cn",
    "work_position": "理想19层/西//",
    "Contact_Phone": "82244301",
    "cell_phone": "",
    "EMPLOYEE_ID": "200914",
    "job": "市场助理",
    "department_id": "101169",
    "deptname": "移动市场部",
    "alias": null,
    "showflag": 1,
    "weibo": "5652685158",
    "ENGLISH_NAME": "hou shuang"
}, {
    "rownumber": "120",
    "empName": "林姗",
    "EMAIL": "linshan3@staff.sina.com.cn",
    "work_position": null,
    "Contact_Phone": null,
    "cell_phone": "",
    "EMPLOYEE_ID": "201032",
    "job": "市场推广",
    "department_id": "101169",
    "deptname": "移动市场部",
    "alias": null,
    "showflag": 1,
    "weibo": "5703427707",
    "ENGLISH_NAME": "LIN SHAN"
}, {
    "rownumber": "121",
    "empName": "张红梅",
    "EMAIL": "hongmei@staff.sina.com.cn",
    "work_position": "理想19层/西/2/7",
    "Contact_Phone": "5926",
    "cell_phone": "",
    "EMPLOYEE_ID": "212",
    "job": "BD项目经理",
    "department_id": "101169",
    "deptname": "移动市场部",
    "alias": null,
    "showflag": 1,
    "weibo": "5652393746",
    "ENGLISH_NAME": "ZHANG HONGMEI"
}, {
    "rownumber": "122",
    "empName": "任鹏",
    "EMAIL": "renpeng@staff.sina.com.cn",
    "work_position": "理想18层/北/7/7",
    "Contact_Phone": "3137",
    "cell_phone": "",
    "EMPLOYEE_ID": "10060",
    "job": "行政专员",
    "department_id": "101165",
    "deptname": "移动事业部",
    "alias": null,
    "showflag": 1,
    "weibo": "2740145847",
    "ENGLISH_NAME": "REN PENG"
}]


